databricks/__init__.py
databricks/_feature_store_pkg_metadata/__init__.py
databricks/_feature_store_pkg_metadata/_core_client_pkg_metadata/__init__.py
databricks/feature_engineering/__init__.py
databricks/feature_engineering/client.py
databricks/feature_engineering/training_set.py
databricks/feature_engineering/upgrade_client.py
databricks/feature_engineering/version.py
databricks/feature_engineering/entities/__init__.py
databricks/feature_engineering/entities/aggregation.py
databricks/feature_engineering/entities/aggregation_function.py
databricks/feature_engineering/entities/cron_schedule.py
databricks/feature_engineering/entities/feature_aggregations.py
databricks/feature_engineering/entities/feature_function.py
databricks/feature_engineering/entities/feature_lookup.py
databricks/feature_engineering/entities/feature_serving_endpoint.py
databricks/feature_engineering/entities/feature_spec_info.py
databricks/feature_engineering/entities/feature_table.py
databricks/feature_engineering/entities/materialized_view_info.py
databricks/feature_engineering/online_store_spec/__init__.py
databricks/feature_engineering/utils/upgrade_utils.py
databricks/feature_store/__init__.py
databricks/feature_store/client.py
databricks/feature_store/decorators.py
databricks/feature_store/mlflow_model.py
databricks/feature_store/training_set.py
databricks/feature_store/version.py
databricks/feature_store/entities/__init__.py
databricks/feature_store/entities/feature.py
databricks/feature_store/entities/feature_function.py
databricks/feature_store/entities/feature_lookup.py
databricks/feature_store/entities/feature_serving_endpoint.py
databricks/feature_store/entities/feature_spec.py
databricks/feature_store/entities/feature_spec_info.py
databricks/feature_store/entities/feature_table.py
databricks/feature_store/online_store_spec/__init__.py
databricks/feature_store/publish_engine/__init__.py
databricks/ml_features/__init__.py
databricks/ml_features/constants.py
databricks_feature_engineering-0.14.0.dist-info/LICENSE.md
databricks_feature_engineering-0.14.0.dist-info/METADATA
databricks_feature_engineering-0.14.0.dist-info/NOTICE.md
databricks_feature_engineering-0.14.0.dist-info/WHEEL
databricks_feature_engineering-0.14.0.dist-info/top_level.txt
databricks_feature_engineering-0.14.0.dist-info/RECORD
