Metadata-Version: 2.1
Name: databricks-feature-engineering
Version: 0.14.0
Summary: Databricks Feature Engineering Client
Author-email: Databricks <feedback@databricks.com>
License: Databricks Proprietary License
Keywords: databricks,feature engineering,feature store
Classifier: Programming Language :: Python :: 3
Requires-Python: >=3.8.10
License-File: LICENSE.md
License-File: NOTICE.md
Requires-Dist: mlflow-skinny[databricks] <4,>=2.16.0
Requires-Dist: pyyaml <7,>=6
Requires-Dist: boto3 <2,>=1.16.7
Requires-Dist: dbl-tempo <1,>=0.1.26
Requires-Dist: azure-cosmos ==4.3.1
Requires-Dist: numpy <3,>=1.19.2
Requires-Dist: protobuf <7,>=5
Requires-Dist: flask <3,>=1.1.2
Requires-Dist: sqlparse <1,>=0.4.0
Requires-Dist: databricks-sdk >=0.76.0
